pytorch_lognormal_mixture/__init__.py
pytorch_lognormal_mixture/log_norm_mix.py
pytorch_lognormal_mixture/utils.py
pytorch_lognormal_mixture/distributions/__init__.py
pytorch_lognormal_mixture/distributions/mixture_same_family.py
pytorch_lognormal_mixture/distributions/normal.py
pytorch_lognormal_mixture/distributions/transformed_distribution.py
pytorch_lognormal_mixture-0.0.1.dist-info/LICENSE
pytorch_lognormal_mixture-0.0.1.dist-info/METADATA
pytorch_lognormal_mixture-0.0.1.dist-info/WHEEL
pytorch_lognormal_mixture-0.0.1.dist-info/top_level.txt
pytorch_lognormal_mixture-0.0.1.dist-info/RECORD
