Metadata-Version: 2.1
Name: pytorch-lognormal-mixture
Version: 0.0.1
Summary: A pip installable version of the lognormal mixture distribution from https://github.com/shchur/ifl-tpp/tree/master/code
Author: Matthew McDermott; Original: Oleksandr Shchur, Marin Bilos, Stephan Guennemann
Author-email: "Matthew B. A. McDermott" <mattmcdermott8@gmail.com>
Project-URL: Homepage, https://github.com/mmcdermott/pytorch_lognormal_mixture
Project-URL: Bug Tracker, https://github.com/mmcdermott/pytorch_lognormal_mixture/issues
Classifier: Programming Language :: Python :: 3
Classifier: License :: OSI Approved :: MIT License
Classifier: Operating System :: OS Independent
Requires-Python: >=3.10
License-File: LICENSE
Requires-Dist: torch (>1.2.0)
